yt_dlp_proxy/__init__.py
yt_dlp_proxy/__main__.py
yt_dlp_proxy/api.py
yt_dlp_proxy/live_test.py
yt_dlp_proxy/proxy_provider.py
yt_dlp_proxy/proxy_providers/onworks_provider.py
yt_dlp_proxy/proxy_providers/sandvpn_provider.py
yt_dlp_proxy/proxy_providers/vnnet_provider.py
yt_dlp_proxy-1.0.7.dist-info/METADATA
yt_dlp_proxy-1.0.7.dist-info/WHEEL
yt_dlp_proxy-1.0.7.dist-info/entry_points.txt
yt_dlp_proxy-1.0.7.dist-info/top_level.txt
yt_dlp_proxy-1.0.7.dist-info/RECORD
