Metadata-Version: 2.4
Name: yt-dlp-proxy
Version: 1.0.7
Summary: A tool for running yt-dlp with the best free proxy
Author-email: Your Name <your.email@example.com>
License: MIT
Requires-Python: >=3.10
Requires-Dist: certifi>=2025.1.31
Requires-Dist: charset-normalizer==3.4.0
Requires-Dist: idna==3.10
Requires-Dist: requests==2.32.3
Requires-Dist: tqdm==4.67.1
Requires-Dist: urllib3==2.2.3
